MongoDBLibrary/__init__.py
MongoDBLibrary/connection_pool.py
MongoDBLibrary/keywords.py
robotframework_mongodb-0.2.2.dist-info/LICENSE
robotframework_mongodb-0.2.2.dist-info/METADATA
robotframework_mongodb-0.2.2.dist-info/WHEEL
robotframework_mongodb-0.2.2.dist-info/RECORD
