Metadata-Version: 2.1
Name: robotframework-mongodb
Version: 0.2.2
Summary: MongoDB test library for Robot Framework.
Home-page: https://github.com/MobyNl/robotframework-mongodblibrary
License: MIT
Keywords: robotframework,mongodb,testing,library
Author: MobyNl
Author-email: markmoberts@gmail.com
Requires-Python: >=3.12,<3.15
Classifier: Framework :: Robot Framework
Classifier: License :: OSI Approved :: MIT License
Classifier: Operating System :: OS Independent
Classifier: Programming Language :: Python :: 3
Classifier: Programming Language :: Python :: 3.12
Provides-Extra: aws
Requires-Dist: pymongo (>=4.13.2,<5.0.0)
Requires-Dist: pymongo-auth-aws (>=1.3.0,<2.0.0) ; extra == "aws"
Requires-Dist: robotframework (>=7.3.2,<8.0.0)
Requires-Dist: robotframework-assertion-engine (>=3.0.3,<4.0.0)
Requires-Dist: robotframework-pythonlibcore (>=4.4.1,<5.0.0)
Project-URL: Repository, https://github.com/MobyNl/robotframework-mongodblibrary
